llmfoo/__init__.py
llmfoo/functions.py
llmfoo-0.5.0.dist-info/LICENSE
llmfoo-0.5.0.dist-info/METADATA
llmfoo-0.5.0.dist-info/WHEEL
llmfoo-0.5.0.dist-info/RECORD
