Metadata-Version: 2.1
Name: llmfoo
Version: 0.5.0
Summary: Automatically make the OpenAI tool JSON Schema, parsing call and constructing the result to the chat model.
Author: Mikko Korpela
Author-email: mikko@robocorp.com
Requires-Python: >=3.10,<4.0
Classifier: Programming Language :: Python :: 3
Classifier: Programming Language :: Python :: 3.10
Classifier: Programming Language :: Python :: 3.11
Classifier: Programming Language :: Python :: 3.12
Requires-Dist: openai (>=1.3.7,<2.0.0)
